sphinx_au_theme/__init__.py
sphinx_au_theme/layout.html
sphinx_au_theme/theme.conf
sphinx_au_theme/static/au.css
sphinx_au_theme/static/au_icons.woff
sphinx_au_theme/static/au_segl.svg
sphinx_au_theme/static/aupassata_bold-webfont.woff2
sphinx_au_theme/static/aupassata_rg-webfont.woff2
sphinx_au_theme/static/favicon.ico
sphinx_au_theme/static/logos.svg
sphinx_au_theme-0.6.0.dist-info/METADATA
sphinx_au_theme-0.6.0.dist-info/WHEEL
sphinx_au_theme-0.6.0.dist-info/entry_points.txt
sphinx_au_theme-0.6.0.dist-info/top_level.txt
sphinx_au_theme-0.6.0.dist-info/RECORD
