Metadata-Version: 2.1
Name: sphinx-au-theme
Version: 0.6.0
Summary: Sphinx theme emulating pages from Aarhus University, Denmark.
Home-page: UNKNOWN
Author: Dan Søndergaard
Author-email: das@birc.au.dk
License: UNKNOWN
Platform: UNKNOWN
Requires-Dist: sphinx
